funding_json/__init__.py
funding_json/model.py
funding_json-0.1.dist-info/LICENSES/CC0-1.0.txt
funding_json-0.1.dist-info/LICENSES/MIT.txt
funding_json-0.1.dist-info/METADATA
funding_json-0.1.dist-info/WHEEL
funding_json-0.1.dist-info/RECORD
