Metadata-Version: 2.1
Name: funding-json
Version: 0.1
Summary: python library for querying and verifying funding.json
Home-page: https://codeberg.org/uniqx/funding-json-py
License: MIT
Author: Michael Pöhn
Author-email: michael@poehn.at
Requires-Python: >=3.8,<4.0
Classifier: License :: OSI Approved :: MIT License
Classifier: Programming Language :: Python :: 3
Classifier: Programming Language :: Python :: 3.8
Classifier: Programming Language :: Python :: 3.9
Classifier: Programming Language :: Python :: 3.10
Classifier: Programming Language :: Python :: 3.11
